Workbook

Sheet Dashboard
A1: RESUMEN GENERAL - FINANZAS PERSONALES
A3: Mes a analizar: | B3: 6 | C3: =CHOOSE(B3,"Enero","Febrero","Marzo","Abril","Mayo","Junio","Julio","Agosto","Septiembre","Octubre","Noviembre","Diciembre")
A4: Año: | B4: 2026
A6: Concepto | B6: Monto | D6: Categoría | E6: Presupuesto | F6: Gastado (mes) | G6: % usado
A7: Ingresos del mes | B7: =SUMIFS(Ingresos!$C:$C,Ingresos!$F:$F,$B$3,Ingresos!$E:$E,$B$4) | D7: Alimentación | E7: 6000 | F7: =SUMIFS(Gastos!$D:$D,Gastos!$B:$B,$D7,Gastos!$G:$G,$B$3,Gastos!$F:$F,$B$4) | G7: =IF(E7=0,0,F7/E7)
A8: Gastos del mes | B8: =SUMIFS(Gastos!$D:$D,Gastos!$G:$G,$B$3,Gastos!$F:$F,$B$4) | D8: Transporte | E8: 3000 | F8: =SUMIFS(Gastos!$D:$D,Gastos!$B:$B,$D8,Gastos!$G:$G,$B$3,Gastos!$F:$F,$B$4) | G8: =IF(E8=0,0,F8/E8)
A9: Ahorro del mes | B9: =B7-B8 | D9: Servicios | E9: 2500 | F9: =SUMIFS(Gastos!$D:$D,Gastos!$B:$B,$D9,Gastos!$G:$G,$B$3,Gastos!$F:$F,$B$4) | G9: =IF(E9=0,0,F9/E9)
A10: Dinero disponible | B10: =SUM(Ingresos!$C:$C)-SUM(Gastos!$D:$D) | D10: Estudios | E10: 2000 | F10: =SUMIFS(Gastos!$D:$D,Gastos!$B:$B,$D10,Gastos!$G:$G,$B$3,Gastos!$F:$F,$B$4) | G10: =IF(E10=0,0,F10/E10)
A11: Fondo para casa | B11: =Metas!C3 | D11: Casa | E11: 4000 | F11: =SUMIFS(Gastos!$D:$D,Gastos!$B:$B,$D11,Gastos!$G:$G,$B$3,Gastos!$F:$F,$B$4) | G11: =IF(E11=0,0,F11/E11)
A12: % destinado al ahorro | B12: =IF(B7=0,0,B9/B7) | D12: Salud | E12: 2000 | F12: =SUMIFS(Gastos!$D:$D,Gastos!$B:$B,$D12,Gastos!$G:$G,$B$3,Gastos!$F:$F,$B$4) | G12: =IF(E12=0,0,F12/E12)
A13: Estado del mes | B13: =IF(B7=0,"Sin ingresos",IF(B8>B7,"ROJO: gastas más de lo que ingresas",IF(B8>0.9*B7,"AMARILLO: cuidado con los gastos","VERDE: vas bien"))) | D13: Entretenimiento | E13: 1500 | F13: =SUMIFS(Gastos!$D:$D,Gastos!$B:$B,$D13,Gastos!$G:$G,$B$3,Gastos!$F:$F,$B$4) | G13: =IF(E13=0,0,F13/E13)
D14: Otros | E14: 1500 | F14: =SUMIFS(Gastos!$D:$D,Gastos!$B:$B,$D14,Gastos!$G:$G,$B$3,Gastos!$F:$F,$B$4) | G14: =IF(E14=0,0,F14/E14)
A16: Evolución mensual (año seleccionado)
A17: Mes | B17: Ingresos | C17: Gastos | D17: Ahorro
A18: Enero | B18: =SUMIFS(Ingresos!$C:$C,Ingresos!$F:$F,1,Ingresos!$E:$E,$B$4) | C18: =SUMIFS(Gastos!$D:$D,Gastos!$G:$G,1,Gastos!$F:$F,$B$4) | D18: =B18-C18
A19: Febrero | B19: =SUMIFS(Ingresos!$C:$C,Ingresos!$F:$F,2,Ingresos!$E:$E,$B$4) | C19: =SUMIFS(Gastos!$D:$D,Gastos!$G:$G,2,Gastos!$F:$F,$B$4) | D19: =B19-C19
A20: Marzo | B20: =SUMIFS(Ingresos!$C:$C,Ingresos!$F:$F,3,Ingresos!$E:$E,$B$4) | C20: =SUMIFS(Gastos!$D:$D,Gastos!$G:$G,3,Gastos!$F:$F,$B$4) | D20: =B20-C20
A21: Abril | B21: =SUMIFS(Ingresos!$C:$C,Ingresos!$F:$F,4,Ingresos!$E:$E,$B$4) | C21: =SUMIFS(Gastos!$D:$D,Gastos!$G:$G,4,Gastos!$F:$F,$B$4) | D21: =B21-C21
A22: Mayo | B22: =SUMIFS(Ingresos!$C:$C,Ingresos!$F:$F,5,Ingresos!$E:$E,$B$4) | C22: =SUMIFS(Gastos!$D:$D,Gastos!$G:$G,5,Gastos!$F:$F,$B$4) | D22: =B22-C22
A23: Junio | B23: =SUMIFS(Ingresos!$C:$C,Ingresos!$F:$F,6,Ingresos!$E:$E,$B$4) | C23: =SUMIFS(Gastos!$D:$D,Gastos!$G:$G,6,Gastos!$F:$F,$B$4) | D23: =B23-C23
A24: Julio | B24: =SUMIFS(Ingresos!$C:$C,Ingresos!$F:$F,7,Ingresos!$E:$E,$B$4) | C24: =SUMIFS(Gastos!$D:$D,Gastos!$G:$G,7,Gastos!$F:$F,$B$4) | D24: =B24-C24
A25: Agosto | B25: =SUMIFS(Ingresos!$C:$C,Ingresos!$F:$F,8,Ingresos!$E:$E,$B$4) | C25: =SUMIFS(Gastos!$D:$D,Gastos!$G:$G,8,Gastos!$F:$F,$B$4) | D25: =B25-C25
A26: Septiembre | B26: =SUMIFS(Ingresos!$C:$C,Ingresos!$F:$F,9,Ingresos!$E:$E,$B$4) | C26: =SUMIFS(Gastos!$D:$D,Gastos!$G:$G,9,Gastos!$F:$F,$B$4) | D26: =B26-C26
A27: Octubre | B27: =SUMIFS(Ingresos!$C:$C,Ingresos!$F:$F,10,Ingresos!$E:$E,$B$4) | C27: =SUMIFS(Gastos!$D:$D,Gastos!$G:$G,10,Gastos!$F:$F,$B$4) | D27: =B27-C27
A28: Noviembre | B28: =SUMIFS(Ingresos!$C:$C,Ingresos!$F:$F,11,Ingresos!$E:$E,$B$4) | C28: =SUMIFS(Gastos!$D:$D,Gastos!$G:$G,11,Gastos!$F:$F,$B$4) | D28: =B28-C28
A29: Diciembre | B29: =SUMIFS(Ingresos!$C:$C,Ingresos!$F:$F,12,Ingresos!$E:$E,$B$4) | C29: =SUMIFS(Gastos!$D:$D,Gastos!$G:$G,12,Gastos!$F:$F,$B$4) | D29: =B29-C29

Sheet Ingresos
A1: REGISTRO DE INGRESOS
A2: Fecha | B2: Descripción | C2: Monto (C$) | E2: Año | F2: Mes
A3: 46174 | B3: Salario | C3: 25000 | E3: =IF(A3="","",YEAR(A3)) | F3: =IF(A3="","",MONTH(A3))
A4: 46178 | B4: Venta freelance | C4: 4500 | E4: =IF(A4="","",YEAR(A4)) | F4: =IF(A4="","",MONTH(A4))
A5: 46188 | B5: Reembolso | C5: 1200 | E5: =IF(A5="","",YEAR(A5)) | F5: =IF(A5="","",MONTH(A5))
A6: 46143 | B6: Salario | C6: 25000 | E6: =IF(A6="","",YEAR(A6)) | F6: =IF(A6="","",MONTH(A6))
A7: 46152 | B7: Bono | C7: 3000 | E7: =IF(A7="","",YEAR(A7)) | F7: =IF(A7="","",MONTH(A7))
E8: =IF(A8="","",YEAR(A8)) | F8: =IF(A8="","",MONTH(A8))
E9: =IF(A9="","",YEAR(A9)) | F9: =IF(A9="","",MONTH(A9))
E10: =IF(A10="","",YEAR(A10)) | F10: =IF(A10="","",MONTH(A10))
E11: =IF(A11="","",YEAR(A11)) | F11: =IF(A11="","",MONTH(A11))
E12: =IF(A12="","",YEAR(A12)) | F12: =IF(A12="","",MONTH(A12))
E13: =IF(A13="","",YEAR(A13)) | F13: =IF(A13="","",MONTH(A13))
E14: =IF(A14="","",YEAR(A14)) | F14: =IF(A14="","",MONTH(A14))
E15: =IF(A15="","",YEAR(A15)) | F15: =IF(A15="","",MONTH(A15))
E16: =IF(A16="","",YEAR(A16)) | F16: =IF(A16="","",MONTH(A16))
E17: =IF(A17="","",YEAR(A17)) | F17: =IF(A17="","",MONTH(A17))
E18: =IF(A18="","",YEAR(A18)) | F18: =IF(A18="","",MONTH(A18))
E19: =IF(A19="","",YEAR(A19)) | F19: =IF(A19="","",MONTH(A19))
... E500: =IF(A500="","",YEAR(A500)) | F500: =IF(A500="","",MONTH(A500))

Sheet Gastos
A1: REGISTRO DE GASTOS
A2: Fecha | B2: Categoría | C2: Descripción | D2: Monto (C$) | F2: Año | G2: Mes
A3: 46175 | B3: Alimentación | C3: Supermercado | D3: 3800 | F3: =IF(A3="","",YEAR(A3)) | G3: =IF(A3="","",MONTH(A3))
A4: 46176 | B4: Transporte | C4: Combustible | D4: 1500 | F4: =IF(A4="","",YEAR(A4)) | G4: =IF(A4="","",MONTH(A4))
A5: 46177 | B5: Servicios | C5: Luz y agua | D5: 1800 | F5: =IF(A5="","",YEAR(A5)) | G5: =IF(A5="","",MONTH(A5))
A6: 46179 | B6: Estudios | C6: Curso online | D6: 1200 | F6: =IF(A6="","",YEAR(A6)) | G6: =IF(A6="","",MONTH(A6))
A7: 46181 | B7: Casa | C7: Reparación | D7: 2500 | F7: =IF(A7="","",YEAR(A7)) | G7: =IF(A7="","",MONTH(A7))
A8: 46183 | B8: Salud | C8: Farmacia | D8: 900 | F8: =IF(A8="","",YEAR(A8)) | G8: =IF(A8="","",MONTH(A8))
A9: 46185 | B9: Entretenimiento | C9: Cine y salida | D9: 1100 | F9: =IF(A9="","",YEAR(A9)) | G9: =IF(A9="","",MONTH(A9))
A10: 46187 | B10: Alimentación | C10: Restaurante | D10: 1400 | F10: =IF(A10="","",YEAR(A10)) | G10: =IF(A10="","",MONTH(A10))
A11: 46145 | B11: Alimentación | C11: Supermercado | D11: 3600 | F11: =IF(A11="","",YEAR(A11)) | G11: =IF(A11="","",MONTH(A11))
A12: 46149 | B12: Transporte | C12: Bus | D12: 800 | F12: =IF(A12="","",YEAR(A12)) | G12: =IF(A12="","",MONTH(A12))
F13: =IF(A13="","",YEAR(A13)) | G13: =IF(A13="","",MONTH(A13))
F14: =IF(A14="","",YEAR(A14)) | G14: =IF(A14="","",MONTH(A14))
F15: =IF(A15="","",YEAR(A15)) | G15: =IF(A15="","",MONTH(A15))
F16: =IF(A16="","",YEAR(A16)) | G16: =IF(A16="","",MONTH(A16))
F17: =IF(A17="","",YEAR(A17)) | G17: =IF(A17="","",MONTH(A17))
F18: =IF(A18="","",YEAR(A18)) | G18: =IF(A18="","",MONTH(A18))
F19: =IF(A19="","",YEAR(A19)) | G19: =IF(A19="","",MONTH(A19))
F20: =IF(A20="","",YEAR(A20)) | G20: =IF(A20="","",MONTH(A20))
F21: =IF(A21="","",YEAR(A21)) | G21: =IF(A21="","",MONTH(A21))
F22: =IF(A22="","",YEAR(A22)) | G22: =IF(A22="","",MONTH(A22))
F23: =IF(A23="","",YEAR(A23)) | G23: =IF(A23="","",MONTH(A23))
F24: =IF(A24="","",YEAR(A24)) | G24: =IF(A24="","",MONTH(A24))
... F500: =IF(A500="","",YEAR(A500)) | G500: =IF(A500="","",MONTH(A500))

Sheet Metas
A1: METAS DE AHORRO
A2: Meta | B2: Objetivo (C$) | C2: Ahorrado (C$) | D2: Falta (C$) | E2: % Avance
A3: Fondo para la casa | B3: 150000 | C3: 35000 | D3: =IF(B3="","",MAX(0,B3-C3)) | E3: =IF(B3="","",IF(B3=0,0,C3/B3))
A4: Fondo de emergencia | B4: 50000 | C4: 18000 | D4: =IF(B4="","",MAX(0,B4-C4)) | E4: =IF(B4="","",IF(B4=0,0,C4/B4))
A5: Negocio propio | B5: 80000 | C5: 12000 | D5: =IF(B5="","",MAX(0,B5-C5)) | E5: =IF(B5="","",IF(B5=0,0,C5/B5))
A6: Vacaciones | B6: 20000 | C6: 6000 | D6: =IF(B6="","",MAX(0,B6-C6)) | E6: =IF(B6="","",IF(B6=0,0,C6/B6))
D7: =IF(B7="","",MAX(0,B7-C7)) | E7: =IF(B7="","",IF(B7=0,0,C7/B7))
D8: =IF(B8="","",MAX(0,B8-C8)) | E8: =IF(B8="","",IF(B8=0,0,C8/B8))
D9: =IF(B9="","",MAX(0,B9-C9)) | E9: =IF(B9="","",IF(B9=0,0,C9/B9))
D10: =IF(B10="","",MAX(0,B10-C10)) | E10: =IF(B10="","",IF(B10=0,0,C10/B10))
D11: =IF(B11="","",MAX(0,B11-C11)) | E11: =IF(B11="","",IF(B11=0,0,C11/B11))
D12: =IF(B12="","",MAX(0,B12-C12)) | E12: =IF(B12="","",IF(B12=0,0,C12/B12))
D13: =IF(B13="","",MAX(0,B13-C13)) | E13: =IF(B13="","",IF(B13=0,0,C13/B13))
D14: =IF(B14="","",MAX(0,B14-C14)) | E14: =IF(B14="","",IF(B14=0,0,C14/B14))
